{
    "Windows Server 2016": {
        "Technical Preview": {
            "9726.0.winmain.140409-1721": {},
            "9727.0.winmain.140410-1715": {},
            "9785.0.fbl_partner_eeap.140629-0030": {},
            "9813.fbl_srv5_nwm_dev.140824-0800": {},
            "9825": {},
            "9834.0.fbl_partner_eeap.140908-0936": {},
            "9841.0.fbl_release.140912-1613": {}
        },
        "Technical Preview 2": {
            "9845.0.fbl_partner_eeap.140922-1425": {},
            "9864.fbl_srv3_rds.141015-1430": {},
            "9865.0.winmain.141015-1514": {},
            "9866.fbl_dnet_ncx.141020-0155": {},
            "9914.0.winmain.141218-1718": {},
            "9926.0.fbl_awesome1501.150119-1648": {},
            "10005.0.winmain_prs.150125-0130": {},
            "10009.0.winmain_prs.150130-0808": {},
            "10014.0.winmain_prs.150205-1859": {},
            "10022.0.fbl_impressive.150216-2206": {},
            "10031.0.fbl_impressive.150301-2107": {},
            "10036.0.fbl_impressive.150306-2322": {},
            "10041.0.fbl_impressive.150313-1821": {},
            "10041.fbl_ur1_netservices.150318-0800": {},
            "10051.0.fbl_impressive.150329-1031": {},
            "10055.0.winmain.150402-1437": {},
            "10056.0.fbl_impressive.150405-1348": {},
            "10064.0.winmain_prs.150413-1856": {},
            "10069": {},
            "10073": {},
            "10074.0.fbl_impressive.150424-1350": {},
            "Technical Preview 2 Update": {
                "10074.1.fbl_impressive_cxe.150425-1755": {},
                "10074.0.fbl_impressive_srvr.150506-0009": {},
                "10074.0.fbl_impressive_srvr.150506-1550": {}
            }
        },
        "Technical Preview 3": {
            "10108.0.winmain_prs.150424-1818": {},
            "10114.0.winmain_prs.150503-0759": {},
            "10120.0.fbl_impressive.150510-1700": {},
            "10125.0.fbl_impressive.150516-2126": {},
            "10125.0.fbl_ur1.150517-1400": {},
            "10128.0.fbl_ur1.150522-1400": {},
            "10130.0.fbl_impressive.150522-2224": {},
            "10135.0.winmain_prs.150531-1700": {},
            "10143.0.fbl_impressive.150609-1823": {},
            "10147.0.fbl_impressive.150613-1600": {},
            "10154.0.fbl_impressive.150620-2234": {},
            "10154.0.fbl_ur1.150622-1400": {},
            "10158.0.fbl_ur1.150629-1400": {},
            "10163.0.winmain_prs.150630-1700": {},
            "10163.0.fbl_ur1.150703-1400": {},
            "10244.0.fbl_ur1.150717-1803": {},
            "10252.0.fbl_ur1.150727-1451": {},
            "10512.1000.th2.150802-1426": {},
            "10513": {},
            "10514.0.th2_release.150808-1529": {},
            "Technical Preview 3 Update": {
                "10514.10.th2_release_svc.151006-1500": {},
                "10514.11.th2_release_svc.151023-1545": {},
                "10514.21.th2_release_svc.160104-1752": {}
            }
        },
        "Technical Preview 4": {
            "10527.0.th2_release.150814-1953": {},
            "10531.0.th2_release.150821-1700": {},
            "10537.0.th2_release.150829-0745": {},
            "10540.0.th2_release.150903-1605": {},
            "10546.0.th2_release.150911-2334": {},
            "10551.0.th2_release.150917-1700": {},
            "10558.0.th2_release.150928-1738": {},
            "10563.0.th2_release.151003-2255": {},
            "10565.0.th2_release.151006-2014": {},
            "10568.0.th2_release.151010-1734": {},
            "10575.0.th2_release.151017-2006": {},
            "10577": {},
            "10580.th2_srv1.151023-1707": {},
            "10586.0.th2_release.151029-1700": {},
            "Technical Preview 4 Update": {
                "10586.3.th2_release_sec.151104-1948": {},
                "10586.11.th2_release.151112-1900": {},
                "10586.17.th2_release.151121-2308": {},
                "10586.29.th2_release.151130-1909": {},
                "10586.36.th2_release.151210-2003": {},
                "10586.63.th2_release.160104-1513": {},
                "10586.71.th2_release.160115-1852": {},
                "10586.103.th2_release.160126-1819": {},
                "10586.104.th2_release.160128-1934": {},
                "10586.119.th2_release.160217-1919": {},
                "10586.122.th2_release_inmarket.160222-1549": {},
                "10586.162.th2_release_sec.160223-1728": {},
                "10586.164.th2_release.160229-1806": {},
                "10586.212.th2_release_sec.160328-1908": {},
                "10586.218.th2_release.160401-1800": {},
                "10586.306.th2_release_sec.160422-1850": {},
                "10586.318.th2_release.160505-1801": {},
                "10586.420.th2_release_sec.160527-1834": {},
                "10586.494.th2_release_sec.160630-1736": {}
            }
        },
        "Technical Preview 5": {
            "10586.1000.th2_srv1_nano_dev2.151112-1500": {},
            "10587.1000.th2_srv1_has_dev1.151201-1500": {},
            "11099.1000.rs1_release.160109-1156": {},
            "11103.1000.rs1_release.160116-0014": {},
            "14257.1000.rs1_release.160131-1800": {},
            "14257.1000.rs1_srv_ps_dev.160201-1500": {},
            "14259.1000.rs1_release.160202-1800": {},
            "14261.1000.rs1_release.160204-1700": {},
            "14267.1000.rs1_release.160213-0213": {},
            "14271.1000.rs1_release.160218-2310": {},
            "14272.1000.rs1_srv_ps_dev.160226-1500": {},
            "14273.1000.rs1_release.160222-1700": {},
            "14276.1000.rs1_release.160225-1700": {},
            "14279.1000.rs1_release.160229-1700": {},
            "14281.1000.rs1_release.160302-2141": {},
            "14282.1000.rs1_srv_ps_dev.160306-1500": {},
            "14282.1002.rs1_onecore_mqsrv_sc.160307-1430": {},
            "14282.1003.rs1_onecore_container_hyp.160306-1800": {},
            "14283.1000.rs1_release.160305-1633": {},
            "14283.1000.rs1_onecore_container_hyp.160307-1800": {},
            "14291.1000.rs1_onecore_container_hyp.160315-1824": {},
            "14291.1001.rs1_release.160314-2254": {},
            "14295.1000.rs1_release.160318-1628": {},
            "14300.1000.rs1_release_svc.160324-1723": {},
            "Technical Preview 5 Update": {
                "14300.1003.rs1_release_svc_d.160410-1700": {},
                "14300.1006.rs1_release_svc.160401-1243": {},
                "14300.1010.rs1_release_svc.160415-2143": {},
                "14300.rs1_release_svc_d.160417-1700": {},
                "14300.1016.rs1_release_svc.160428-1819": {},
                "14300.1017.rs1_release_svc_d.160621-1700": {},
                "14300.1030.rs1_release_svc.160603-1734": {},
                "14300.1043.rs1_release_svc.160621-1806": {},
                "14300.1045.rs1_release_svc.160705-1059": {},
                "14300.1052.rs1_release_svc.160721-1818": {},
                "14300.1054.rs1_release_svc.160726-1817": {},
                "14300.1061.rs1_release_svc.160907-0755": {},
                "14300.1066.rs1_release_svc.160929-1758": {},
                "14300.1071.rs1_release_svc.161024-1753": {}
            }
        },
        "Pre-RTM": {
            "14316.1000.rs1_release.160402-2217": {},
            "14322.1000.rs1_release.160411-1700": {},
            "14324.1001.rs1_onecore_mqsrv_sc.160414-1853": {},
            "14325.1000.rs1_srv_has_dev1.160418-1500": {},
            "14328.1000.rs1_release.160418-1609": {},
            "14332.1001.rs1_release.160422-1940": {},
            "14337.1000.rs1_release.160429-1700": {},
            "14342.1000.rs1_release.160506-1708": {},
            "14347.1000.rs1_release.160513-1723": {},
            "14349.1000.rs1_release.160517-1700": {},
            "14350.1000.rs1_release.160518-1700": {},
            "14351.1000.rs1_release.160519-1741": {},
            "14352.1002.rs1_release.160522-1930": {},
            "14354.1000.rs1_release.160524-1700": {},
            "14355.1000.rs1_release.160525-1714": {},
            "14355.1000.rs1_release_prs.160525-1912": {},
            "14361.1000.rs1_release_prs.160603-2123": {},
            "14363.0.rs1_release.160607-1700": {},
            "14366.0.rs1_release.160610-1700": {},
            "14367.0.rs1_release.160613-1700": {},
            "14367.1000.rs1_onecore_container_hyp.160614-1704": {},
            "14369.0.rs1_release.160615-1700": {},
            "14371.1000.rs1_release_prs.160617-1933": {},
            "14376.0.rs1_release.160624-1700": {},
            "14379.1000.rs1_srv_ps_dev.160628-1500": {},
            "14387.1000.rs1_srv_ps_dev.160711-1500": {}
        },
        "RTM": {
            "14393.0.rs1_release.160715-1616": {}
        },
        "Post-RTM": {
            "14393.0.rs1_release_srvmedia.160808-1702": {},
            "14393.1000.rs1_release_d_srv.160912-1700": {},
            "14393.1000.rs1_release_d_srv.160913-1700": {},
            "14877.1000.rs_onecore_base_sc.160710-1430": {},
            "14901.1000.rs_onecore_base_sc.160809-1841": {},
            "15033.rs_onecore_base_sc.170212-1430": {}
        }
    }
}